cq_vscode/__init__.py
cq_vscode/animation.py
cq_vscode/show.py
cq_vscode-0.29.0.dist-info/LICENSE
cq_vscode-0.29.0.dist-info/METADATA
cq_vscode-0.29.0.dist-info/WHEEL
cq_vscode-0.29.0.dist-info/top_level.txt
cq_vscode-0.29.0.dist-info/RECORD
